<annotation>
  <folder>XML</folder>
  <filename>Pothole-449.jpg</filename>
  <source>
      <database>Pothole</database>
  </source>
  <size>
    <width>620</width>
    <height>412</height>
    <depth>3</depth>
  </size>
  <segmented>0</segmented>
  <object>
    <name>pothole</name>
    <pose>Unspecified</pose>
    <truncated>0</truncated>
    <difficult>0</difficult>
    <bndbox>
      <xmin>85</xmin>
      <ymin>281</ymin>
      <xmax>302</xmax>
      <ymax>337</ymax>
    </bndbox>
  </object>
</annotation>
